valgrind_parser/__init__.py
valgrind_parser/valgrind_log_parser.py
valgrind_parser/data/__init__.py
valgrind_parser/data/valgrind_regexes.json
valgrind_parser/utils/__init__.py
valgrind_parser/utils/decorators.py
valgrind_parser/utils/html_converter.py
valgrind_parser/utils/json_helper.py
valgrind_parser-2.0.3.dist-info/LICENSE
valgrind_parser-2.0.3.dist-info/METADATA
valgrind_parser-2.0.3.dist-info/WHEEL
valgrind_parser-2.0.3.dist-info/top_level.txt
valgrind_parser-2.0.3.dist-info/RECORD
