Metadata-Version: 2.1
Name: valgrind-parser
Version: 2.0.3
Summary: The valgrind logs parser. Creates the html report from txt logs.
Home-page: https://github.com/siddheshsathe/Valgrind-Log-Parser
Author: Siddhesh Sathe
Author-email: siddheshsathe@rediffmail.com
License: GNU General Public License v3.0
Platform: UNKNOWN
Requires-Dist: json2table
